odoo/addons/web_widget_ckeditor/README.rst
odoo/addons/web_widget_ckeditor/__init__.py
odoo/addons/web_widget_ckeditor/__manifest__.py
odoo/addons/web_widget_ckeditor/i18n/web_widget_ckeditor.pot
odoo/addons/web_widget_ckeditor/models/__init__.py
odoo/addons/web_widget_ckeditor/models/ir_config_parameter.py
odoo/addons/web_widget_ckeditor/readme/CONFIGURE.rst
odoo/addons/web_widget_ckeditor/readme/CONTRIBUTORS.rst
odoo/addons/web_widget_ckeditor/readme/DESCRIPTION.rst
odoo/addons/web_widget_ckeditor/readme/ROADMAP.rst
odoo/addons/web_widget_ckeditor/static/description/icon.png
odoo/addons/web_widget_ckeditor/static/description/index.html
odoo/addons/web_widget_ckeditor/static/lib/ckeditor/LICENSE.md
odoo/addons/web_widget_ckeditor/static/lib/ckeditor/README.md
odoo/addons/web_widget_ckeditor/static/lib/ckeditor/package-lock.json
odoo/addons/web_widget_ckeditor/static/lib/ckeditor/package.json
odoo/addons/web_widget_ckeditor/static/lib/ckeditor/webpack.config.js
odoo/addons/web_widget_ckeditor/static/lib/ckeditor/build/ckeditor.js
odoo/addons/web_widget_ckeditor/static/lib/ckeditor/build/ckeditor.js.map
odoo/addons/web_widget_ckeditor/static/lib/ckeditor/build/translations/af.js
odoo/addons/web_widget_ckeditor/static/lib/ckeditor/build/translations/ar.js
odoo/addons/web_widget_ckeditor/static/lib/ckeditor/build/translations/ast.js
odoo/addons/web_widget_ckeditor/static/lib/ckeditor/build/translations/az.js
odoo/addons/web_widget_ckeditor/static/lib/ckeditor/build/translations/bg.js
odoo/addons/web_widget_ckeditor/static/lib/ckeditor/build/translations/ca.js
odoo/addons/web_widget_ckeditor/static/lib/ckeditor/build/translations/cs.js
odoo/addons/web_widget_ckeditor/static/lib/ckeditor/build/translations/da.js
odoo/addons/web_widget_ckeditor/static/lib/ckeditor/build/translations/de-ch.js
odoo/addons/web_widget_ckeditor/static/lib/ckeditor/build/translations/de.js
odoo/addons/web_widget_ckeditor/static/lib/ckeditor/build/translations/el.js
odoo13_addon_web_widget_ckeditor-13.0.1.0.1.dev2.dist-info/METADATA
odoo13_addon_web_widget_ckeditor-13.0.1.0.1.dev2.dist-info/WHEEL
odoo13_addon_web_widget_ckeditor-13.0.1.0.1.dev2.dist-info/top_level.txt
odoo13_addon_web_widget_ckeditor-13.0.1.0.1.dev2.dist-info/RECORD
